multivelovae/__init__.py
multivelovae/plotting.py
multivelovae/plotting_chrom.py
multivelovae/analysis/__init__.py
multivelovae/analysis/evaluation.py
multivelovae/analysis/evaluation_util.py
multivelovae/analysis/perf_logger.py
multivelovae/model/__init__.py
multivelovae/model/differential_chrom.py
multivelovae/model/model_util_chrom.py
multivelovae/model/training_data_chrom.py
multivelovae/model/vae_chrom.py
multivelovae/model/velocity_chrom.py
multivelovae-0.1.0.dist-info/licenses/LICENSE
multivelovae-0.1.0.dist-info/METADATA
multivelovae-0.1.0.dist-info/WHEEL
multivelovae-0.1.0.dist-info/top_level.txt
multivelovae-0.1.0.dist-info/RECORD
